speedygui/__init__.py
speedygui/predictor.py
speedygui/predictor_app.py
speedygui/utils.py
speedygui-0.1.3.dist-info/METADATA
speedygui-0.1.3.dist-info/WHEEL
speedygui-0.1.3.dist-info/top_level.txt
speedygui-0.1.3.dist-info/RECORD
