Metadata-Version: 2.1
Name: speedygui
Version: 0.1.3
Summary: A simple template for creating GUI PyTorch medical image segmentation applications
Author: Justin Charney
Author-email: justin.charney@gmail.com
Classifier: Programming Language :: Python :: 3
Classifier: License :: OSI Approved :: MIT License
Classifier: Operating System :: OS Independent
Requires-Python: >=3.6
Requires-Dist: toga
Requires-Dist: torch
Requires-Dist: pillow
Requires-Dist: torchvision
Requires-Dist: scikit-image
